memoryx/__init__.py
memoryx-0.1.0.dist-info/METADATA
memoryx-0.1.0.dist-info/WHEEL
memoryx-0.1.0.dist-info/RECORD
