Metadata-Version: 2.4
Name: memoryx
Version: 0.1.0
Summary: A very basic example Python package
Author-email: singhastra <singhisabhaypratap@gmail.com>
